txtrader_monitor/__init__.py
txtrader_monitor/channel.py
txtrader_monitor/connection_state.py
txtrader_monitor/monitor.py
txtrader_monitor/version.py
txtrader_monitor-1.1.8.data/data/LICENSE
txtrader_monitor-1.1.8.data/data/requirements.txt
txtrader_monitor-1.1.8.dist-info/LICENSE
txtrader_monitor-1.1.8.dist-info/METADATA
txtrader_monitor-1.1.8.dist-info/WHEEL
txtrader_monitor-1.1.8.dist-info/entry_points.txt
txtrader_monitor-1.1.8.dist-info/top_level.txt
txtrader_monitor-1.1.8.dist-info/RECORD
