Metadata-Version: 2.1
Name: txtrader-monitor
Version: 1.1.8
Summary: TxTrader Securities Trading API Monitor
Home-page: https://github.com/rstms/txtrader_monitor/
Author: Matt Krueger
Author-email: mkrueger@rstms.net
License: MIT
Keywords: trading api txtrader twisted
Platform: UNKNOWN
Classifier: Programming Language :: Python :: 3
Classifier: License :: OSI Approved :: MIT License
Classifier: Operating System :: OS Independent
Classifier: Environment :: Console
Requires-Python: >=3.7
Requires-Dist: twisted (==20.3.0)
Requires-Dist: click (==7.1.2)
Requires-Dist: ujson (==3.1.0)
